pyongc/__init__.py
pyongc/data.py
pyongc/exceptions.py
pyongc/ongc.db
pyongc/ongc.db.license
pyongc/ongc.py
pyongc/scripts/__init__.py
pyongc/scripts/ongc.py
pyongc-1.2.0.dist-info/METADATA
pyongc-1.2.0.dist-info/WHEEL
pyongc-1.2.0.dist-info/entry_points.txt
pyongc-1.2.0.dist-info/licenses/LICENSES/CC-BY-SA-4.0.txt
pyongc-1.2.0.dist-info/licenses/LICENSES/MIT.txt
pyongc-1.2.0.dist-info/RECORD
