Metadata-Version: 2.4
Name: PyOngc
Version: 1.2.0
Summary: Python interface to OpenNGC database data
Project-URL: homepage, https://github.com/mattiaverga/PyOngc
Author-email: Mattia Verga <mattia.verga@tiscali.it>
License-Expression: MIT AND CC-BY-SA-4.0
License-File: LICENSES/CC-BY-SA-4.0.txt
License-File: LICENSES/MIT.txt
Keywords: astronomy,database
Classifier: Development Status :: 5 - Production/Stable
Classifier: Intended Audience :: Developers
Classifier: Intended Audience :: Science/Research
Classifier: License :: OSI Approved :: MIT License
Classifier: Operating System :: OS Independent
Classifier: Programming Language :: Python
Classifier: Programming Language :: Python :: 3
Classifier: Programming Language :: Python :: 3.9
Classifier: Programming Language :: Python :: 3.10
Classifier: Programming Language :: Python :: 3.11
Classifier: Programming Language :: Python :: 3.12
Classifier: Programming Language :: Python :: 3.13
Classifier: Programming Language :: Python :: 3.14
Classifier: Topic :: Database
Classifier: Topic :: Scientific/Engineering :: Astronomy
Requires-Python: >=3.9
Requires-Dist: click~=8.0
Requires-Dist: numpy~=2.0
Provides-Extra: data
Requires-Dist: pandas~=2.0; extra == 'data'
Provides-Extra: development
Requires-Dist: pytest; extra == 'development'
Requires-Dist: pytest-cov; extra == 'development'
Requires-Dist: pytest-doctestplus; extra == 'development'
Requires-Dist: ruff; extra == 'development'
Provides-Extra: docs
Requires-Dist: pandas~=2.0; extra == 'docs'
Requires-Dist: sphinx-rtd-theme~=3.0; extra == 'docs'
Requires-Dist: sphinx~=8.0; extra == 'docs'
